miniboa/__init__.py
miniboa/mbasync.py
miniboa/telnet.py
miniboa/xterm.py
miniboa-1.0.9.dist-info/LICENSE
miniboa-1.0.9.dist-info/METADATA
miniboa-1.0.9.dist-info/WHEEL
miniboa-1.0.9.dist-info/top_level.txt
miniboa-1.0.9.dist-info/RECORD
