Metadata-Version: 2.1
Name: miniboa
Version: 1.0.9
Summary: Asynchronous, single-threaded, poll-based Telnet server
Home-page: https://github.com/shmup/miniboa
Author: Jared Miller
Author-email: jared@smell.flowers
Maintainer: Jared Miller
Maintainer-email: jared@smell.flowers
License: Apache 2
Keywords: mud,tcp,telnet
Classifier: Development Status :: 5 - Production/Stable
Classifier: Intended Audience :: Developers
Classifier: Natural Language :: English
Classifier: License :: OSI Approved :: Apache Software License
Classifier: Operating System :: OS Independent
Classifier: Programming Language :: Python
Classifier: Programming Language :: Python :: 2
Classifier: Programming Language :: Python :: 2.7
Classifier: Programming Language :: Python :: 3
Classifier: Programming Language :: Python :: 3.7
Classifier: Programming Language :: Python :: 3.8
Classifier: Programming Language :: Python :: 3.9
Classifier: Programming Language :: Python :: 3.10
Classifier: Topic :: Software Development :: Libraries
License-File: LICENSE
